xmltv/__init__.py
xmltv/xmltv_helpers.py
xmltv/data/rating_info.json
xmltv/models/__init__.py
xmltv/models/xmltv.py
xmltv/resources/xmltv.xsd
py_xmltv-1.0.8.dist-info/METADATA
py_xmltv-1.0.8.dist-info/WHEEL
py_xmltv-1.0.8.dist-info/top_level.txt
py_xmltv-1.0.8.dist-info/RECORD
