Metadata-Version: 2.1
Name: py-xmltv
Version: 1.0.8
Summary: An Auto-Generated Python Module for Reading and Writing XMLTV Files based on the official XMLTV XSD and DTD schema.
Home-page: https://github.com/chris102994/py-xmltv
Author: Chris102994
Author-email: chris102994@yahoo.com
License: LGPL-3.0+
Project-URL: Source, https://github.com/chris102994/py-xmltv
Project-URL: Changelog, https://github.com/chris102994/py-xmltv/blob/master/CHANGELOG.md
Keywords: tv,,xml,,xmltv,,xsd,,xsdata
Platform: UNKNOWN
Classifier: Development Status :: 5 - Production/Stable
Classifier: Intended Audience :: Developers
Classifier: License :: OSI Approved :: GNU Library or Lesser General Public License (LGPL)
Classifier: Operating System :: OS Independent
Classifier: Programming Language :: Python
Classifier: Programming Language :: Python :: 3
Classifier: Programming Language :: Python :: 3 :: Only
Classifier: Programming Language :: Python :: 3.6
Classifier: Programming Language :: Python :: 3.7
Classifier: Programming Language :: Python :: 3.8
Classifier: Programming Language :: Python :: 3.9
Classifier: Topic :: Software Development :: Libraries :: Python Modules
Requires-Python: >=3.6
Requires-Dist: setuptools
Requires-Dist: sh
Requires-Dist: xsdata
Provides-Extra: build
Requires-Dist: jingtrang ; extra == 'build'
Requires-Dist: pytest ; extra == 'build'
Requires-Dist: sh ; extra == 'build'
Requires-Dist: xsdata[cli] ; extra == 'build'
Provides-Extra: test
Requires-Dist: pytest ; extra == 'test'
Requires-Dist: tox ; extra == 'test'
